{
  "machine_count": 75,
  "interval_ms": 250,
  "machine_id": "machine-0001-m75-i250",
  "cid": "QmYfHNEsd3RiYdeW9AqTLiFyQ2KLn1KAPV8DnmStzs7wtf",
  "hash": "bd9576ce78173f4218214f1849bb7d231d97215d590d817cafea646e05609ed0",
  "invoke_ok": true,
  "verify_ok": true,
  "history_ok": true,
  "history_length": 48,
  "cid_matches_history": false,
  "hash_matches_history": false,
  "success_end_to_end": false,
  "timing_ms": {
    "snapshot_hash": 7,
    "ipfs_add_cid": 77,
    "ipfs_cat_check": 17,
    "fabric_submit_commit": 661,
    "fabric_query_phase": 152,
    "end_to_end_total": 914
  }
}