{
  "machine_count": 100,
  "interval_ms": 1000,
  "machine_id": "machine-0001-m100-i1000",
  "cid": "QmSLW8LLCPRokCdZQhLBDYhgDwxJ8qVww9Fa9Rir6mhzde",
  "hash": "d49dc249bdb977908467c75e642b17275b1689d6005dc4a752313fade86ff7c4",
  "invoke_ok": true,
  "verify_ok": true,
  "history_ok": true,
  "history_length": 58,
  "cid_matches_history": false,
  "hash_matches_history": false,
  "success_end_to_end": false,
  "timing_ms": {
    "snapshot_hash": 9,
    "ipfs_add_cid": 79,
    "ipfs_cat_check": 17,
    "fabric_submit_commit": 661,
    "fabric_query_phase": 157,
    "end_to_end_total": 923
  }
}